{
  "POIs": [
    {
      "fit": [
        -0.18933741748332977,
        0.0,
        0.208418607711792
      ],
      "name": "r"
    }
  ],
  "method": "default",
  "params": [
    {
      "fit": [
        -0.44167467951774597,
        0.0,
        0.7584986090660095
      ],
      "groups": [],
      "impact_r": 0.025682199746370316,
      "name": "Conversion",
      "prefit": [
        -1.0,
        0.0,
        1.0
      ],
      "r": [
        0.025682199746370316,
        0.0,
        -0.01306636817753315
      ],
      "type": "Gaussian"
    },
    {
      "fit": [
        -0.9949138164520264,
        0.0,
        0.9952771067619324
      ],
      "groups": [],
      "impact_r": 0.0059148469008505344,
      "name": "JetEn",
      "prefit": [
        -1.0,
        0.0,
        1.0
      ],
      "r": [
        -0.00033646728843450546,
        0.0,
        -0.0059148469008505344
      ],
      "type": "Gaussian"
    },
    {
      "fit": [
        -0.9883841872215271,
        0.0,
        0.9896009564399719
      ],
      "groups": [],
      "impact_r": 0.002630759496241808,
      "name": "JetRes",
      "prefit": [
        -1.0,
        0.0,
        1.0
      ],
      "r": [
        0.0004491815052460879,
        0.0,
        -0.002630759496241808
      ],
      "type": "Gaussian"
    },
    {
      "fit": [
        -0.9999980926513672,
        1.0602718703012215e-10,
        0.9999980330467224
      ],
      "groups": [],
      "impact_r": 0.00031080869628641317,
      "name": "L1Prefire",
      "prefit": [
        -0.9999999999999999,
        0.0,
        0.9999999999999999
      ],
      "r": [
        0.00031080833286978304,
        -3.63416630122515e-10,
        -0.000310536619508639
      ],
      "type": "Gaussian"
    },
    {
      "fit": [
        -0.9804801344871521,
        0.0,
        0.995536208152771
      ],
      "groups": [],
      "impact_r": 0.0024326303973793983,
      "name": "MuonEn",
      "prefit": [
        -1.0,
        0.0,
        1.0
      ],
      "r": [
        0.0016190962633118033,
        0.0,
        -0.0024326303973793983
      ],
      "type": "Gaussian"
    },
    {
      "fit": [
        -0.9997131824493408,
        0.0,
        0.9996978044509888
      ],
      "groups": [],
      "impact_r": 0.0038682587910443544,
      "name": "MuonIDSF",
      "prefit": [
        -0.9999999999999999,
        0.0,
        0.9999999999999999
      ],
      "r": [
        0.0038682587910443544,
        0.0,
        -0.0038137456867843866
      ],
      "type": "Gaussian"
    },
    {
      "fit": [
        -0.4571239948272705,
        0.0,
        0.396536648273468
      ],
      "groups": [],
      "impact_r": 0.10235944390296936,
      "name": "Nonprompt",
      "prefit": [
        -1.0,
        0.0,
        1.0
      ],
      "r": [
        0.09905432164669037,
        0.0,
        -0.10235944390296936
      ],
      "type": "Gaussian"
    },
    {
      "fit": [
        -0.9980998635292053,
        0.0,
        0.9976606369018555
      ],
      "groups": [],
      "impact_r": 0.00161850661970675,
      "name": "PileupReweight",
      "prefit": [
        -1.0,
        0.0,
        1.0
      ],
      "r": [
        0.0005386790726333857,
        0.0,
        -0.00161850661970675
      ],
      "type": "Gaussian"
    },
    {
      "fit": [
        -0.9997119903564453,
        0.0,
        0.9996964931488037
      ],
      "groups": [],
      "impact_r": 0.003869291627779603,
      "name": "lumi_13TeV",
      "prefit": [
        -0.9999999999999999,
        0.0,
        0.9999999999999999
      ],
      "r": [
        0.003869291627779603,
        0.0,
        -0.0038296235725283623
      ],
      "type": "Gaussian"
    },
    {
      "fit": [
        -0.8314279317855835,
        -1.3095148460706696e-05,
        0.8777936100959778
      ],
      "groups": [],
      "impact_r": 0.010982329957187176,
      "name": "prop_binbin1_bin0",
      "prefit": [
        -0.9999999999999999,
        0.0,
        0.9999999999999999
      ],
      "r": [
        -0.005256422329694033,
        0.0,
        0.010982329957187176
      ],
      "type": "Gaussian"
    },
    {
      "fit": [
        -0.8897820115089417,
        -1.4526638551615179e-05,
        0.9239415526390076
      ],
      "groups": [],
      "impact_r": 0.006725333631038666,
      "name": "prop_binbin1_bin1",
      "prefit": [
        -0.9999999999999999,
        0.0,
        0.9999999999999999
      ],
      "r": [
        -0.0038903290405869484,
        0.0,
        0.006725333631038666
      ],
      "type": "Gaussian"
    },
    {
      "fit": [
        -0.8975493907928467,
        -0.00013462218339554965,
        0.9004073143005371
      ],
      "groups": [],
      "impact_r": 0.07334712892770767,
      "name": "prop_binbin1_bin10",
      "prefit": [
        -0.9999999999999999,
        0.0,
        0.9999999999999999
      ],
      "r": [
        0.07334712892770767,
        0.0,
        -0.05023469403386116
      ],
      "type": "Gaussian"
    },
    {
      "fit": [
        -0.7558891177177429,
        -6.442488665925339e-05,
        0.897226095199585
      ],
      "groups": [],
      "impact_r": 0.03156546130776405,
      "name": "prop_binbin1_bin11",
      "prefit": [
        -0.9999999999999999,
        0.0,
        0.9999999999999999
      ],
      "r": [
        0.03156546130776405,
        0.0,
        -0.006556935142725706
      ],
      "type": "Gaussian"
    },
    {
      "fit": [
        -0.7285531759262085,
        -4.9274756747763604e-05,
        0.8171069025993347
      ],
      "groups": [],
      "impact_r": 0.029406163841485977,
      "name": "prop_binbin1_bin12",
      "prefit": [
        -0.9999999999999999,
        0.0,
        0.9999999999999999
      ],
      "r": [
        0.029406163841485977,
        0.0,
        -0.0046370611526072025
      ],
      "type": "Gaussian"
    },
    {
      "fit": [
        -0.8698173761367798,
        -3.108458258793689e-05,
        0.9034249186515808
      ],
      "groups": [],
      "impact_r": 0.008358826860785484,
      "name": "prop_binbin1_bin13",
      "prefit": [
        -0.9999999999999999,
        0.0,
        0.9999999999999999
      ],
      "r": [
        -0.0014498828677460551,
        0.0,
        0.008358826860785484
      ],
      "type": "Gaussian"
    },
    {
      "fit": [
        -0.8624844551086426,
        -1.9909350157831796e-05,
        0.8995432257652283
      ],
      "groups": [],
      "impact_r": 0.005745438858866692,
      "name": "prop_binbin1_bin14",
      "prefit": [
        -0.9999999999999999,
        0.0,
        0.9999999999999999
      ],
      "r": [
        0.002560326363891363,
        0.0,
        0.005745438858866692
      ],
      "type": "Gaussian"
    },
    {
      "fit": [
        -0.8230133056640625,
        -1.865406011347659e-05,
        0.8780370950698853
      ],
      "groups": [],
      "impact_r": 0.012694521807134151,
      "name": "prop_binbin1_bin15",
      "prefit": [
        -0.9999999999999999,
        0.0,
        0.9999999999999999
      ],
      "r": [
        -0.004525655880570412,
        0.0,
        0.012694521807134151
      ],
      "type": "Gaussian"
    },
    {
      "fit": [
        -0.8926748633384705,
        -1.0483386176929343e-05,
        0.9219875335693359
      ],
      "groups": [],
      "impact_r": 0.012359593994915485,
      "name": "prop_binbin1_bin16",
      "prefit": [
        -0.9999999999999999,
        0.0,
        0.9999999999999999
      ],
      "r": [
        -0.01135214976966381,
        0.0,
        0.012359593994915485
      ],
      "type": "Gaussian"
    },
    {
      "fit": [
        -0.8267670273780823,
        -1.1183286915183999e-05,
        0.8810440301895142
      ],
      "groups": [],
      "impact_r": 0.006540289148688316,
      "name": "prop_binbin1_bin17",
      "prefit": [
        -0.9999999999999999,
        0.0,
        0.9999999999999999
      ],
      "r": [
        0.0011333698639646173,
        0.0,
        0.006540289148688316
      ],
      "type": "Gaussian"
    },
    {
      "fit": [
        -0.8234047293663025,
        -9.143008355749771e-06,
        0.8734186291694641
      ],
      "groups": [],
      "impact_r": 0.015022559091448784,
      "name": "prop_binbin1_bin18",
      "prefit": [
        -0.9999999999999999,
        0.0,
        0.9999999999999999
      ],
      "r": [
        -0.013119961135089397,
        0.0,
        0.015022559091448784
      ],
      "type": "Gaussian"
    },
    {
      "fit": [
        -0.8914028406143188,
        -8.484464160574134e-06,
        0.9224805235862732
      ],
      "groups": [],
      "impact_r": 0.017566338181495667,
      "name": "prop_binbin1_bin19",
      "prefit": [
        -0.9999999999999999,
        0.0,
        0.9999999999999999
      ],
      "r": [
        -0.017566338181495667,
        0.0,
        0.01625809632241726
      ],
      "type": "Gaussian"
    },
    {
      "fit": [
        -0.721204400062561,
        -1.4222580830391962e-05,
        0.8212517499923706
      ],
      "groups": [],
      "impact_r": 0.011721069924533367,
      "name": "prop_binbin1_bin2",
      "prefit": [
        -0.9999999999999999,
        0.0,
        0.9999999999999999
      ],
      "r": [
        -0.00014563511649612337,
        0.0,
        0.011721069924533367
      ],
      "type": "Gaussian"
    },
    {
      "fit": [
        -0.883725643157959,
        -1.716419865260832e-05,
        0.9145910739898682
      ],
      "groups": [],
      "impact_r": 0.008665923960506916,
      "name": "prop_binbin1_bin3",
      "prefit": [
        -0.9999999999999999,
        0.0,
        0.9999999999999999
      ],
      "r": [
        -0.005724367685616016,
        0.0,
        0.008665923960506916
      ],
      "type": "Gaussian"
    },
    {
      "fit": [
        -0.6995480060577393,
        -1.785608401405625e-05,
        0.8206145763397217
      ],
      "groups": [],
      "impact_r": 0.01954304240643978,
      "name": "prop_binbin1_bin4",
      "prefit": [
        -0.9999999999999999,
        0.0,
        0.9999999999999999
      ],
      "r": [
        -0.014451947063207626,
        0.0,
        0.01954304240643978
      ],
      "type": "Gaussian"
    },
    {
      "fit": [
        -0.879887580871582,
        -2.7493828383740038e-05,
        0.9123481512069702
      ],
      "groups": [],
      "impact_r": 0.011465726420283318,
      "name": "prop_binbin1_bin5",
      "prefit": [
        -0.9999999999999999,
        0.0,
        0.9999999999999999
      ],
      "r": [
        -0.00807252898812294,
        0.0,
        0.011465726420283318
      ],
      "type": "Gaussian"
    },
    {
      "fit": [
        -0.8148198127746582,
        -3.4303822758374736e-05,
        0.8585107326507568
      ],
      "groups": [],
      "impact_r": 0.005633401218801737,
      "name": "prop_binbin1_bin6",
      "prefit": [
        -0.9999999999999999,
        0.0,
        0.9999999999999999
      ],
      "r": [
        0.004133801907300949,
        0.0,
        0.005633401218801737
      ],
      "type": "Gaussian"
    },
    {
      "fit": [
        -0.8633767366409302,
        -6.113555718911812e-05,
        0.8909009695053101
      ],
      "groups": [],
      "impact_r": 0.0312351044267416,
      "name": "prop_binbin1_bin7",
      "prefit": [
        -0.9999999999999999,
        0.0,
        0.9999999999999999
      ],
      "r": [
        0.0312351044267416,
        0.0,
        -0.01228044182062149
      ],
      "type": "Gaussian"
    },
    {
      "fit": [
        -0.9629030227661133,
        -0.00011228307266719639,
        0.9651556015014648
      ],
      "groups": [],
      "impact_r": 0.047956667840480804,
      "name": "prop_binbin1_bin8",
      "prefit": [
        -0.9999999999999999,
        0.0,
        0.9999999999999999
      ],
      "r": [
        0.047956667840480804,
        0.0,
        -0.03893178328871727
      ],
      "type": "Gaussian"
    },
    {
      "fit": [
        -0.91617351770401,
        -0.00010773781104944646,
        0.9270222187042236
      ],
      "groups": [],
      "impact_r": 0.04399196803569794,
      "name": "prop_binbin1_bin9",
      "prefit": [
        -0.9999999999999999,
        0.0,
        0.9999999999999999
      ],
      "r": [
        0.04399196803569794,
        0.0,
        -0.02534417062997818
      ],
      "type": "Gaussian"
    }
  ]
}